sopy/__init__.py
sopy/amplitude/__init__.py
sopy/amplitude/amplitude.py
sopy/component/__init__.py
sopy/component/component.py
sopy/component/momentum.py
sopy/pyscf/__init__.py
sopy/pyscf/ext.py
sopy/tensorly/__init__.py
sopy/tensorly/ext.py
sopy/vector/__init__.py
sopy/vector/operand.py
sopy/vector/vector.py
sopy_quantum-1.4.0.dist-info/licenses/LICENSE.txt
sopy_quantum-1.4.0.dist-info/METADATA
sopy_quantum-1.4.0.dist-info/WHEEL
sopy_quantum-1.4.0.dist-info/top_level.txt
sopy_quantum-1.4.0.dist-info/RECORD
