Metadata-Version: 2.4
Name: sopy-quantum
Version: 1.4.0
Summary: Representation and Decomposition with Sums of Product for Operations in separated dimensions. Now using bandlimit place data on lattice.
Author-email: Jonathan Jerke <jonathan@quantumgalaxies.org>
License-Expression: MIT
Project-URL: Homepage, https://sopy.quantumgalaxies.org
Project-URL: Issues, https://github.com/quantumgalaxies/sopy/issues
Classifier: Programming Language :: Python :: 3
Classifier: Operating System :: OS Independent
Classifier: Intended Audience :: Science/Research
Classifier: Intended Audience :: Developers
Requires-Python: >=3.11
License-File: LICENSE.txt
Requires-Dist: tensorflow>=2.16.1
Requires-Dist: scikit-learn>=1.6.1
Requires-Dist: bandlimit>=1.2.4
Provides-Extra: pyscf
Requires-Dist: pyscf>=2.11.0; extra == "pyscf"
Provides-Extra: tensorly
Requires-Dist: tensorly>=0.9.0; extra == "tensorly"
Dynamic: license-file
